{"assets/images/Hover.png":["assets/images/Hover.png"],"assets/images/Hover_flip.png":["assets/images/Hover_flip.png"],"assets/images/Intreaction_design.png":["assets/images/Intreaction_design.png"],"assets/images/Logo.png":["assets/images/Logo.png"],"assets/images/add.png":["assets/images/add.png"],"assets/images/add1.png":["assets/images/add1.png"],"assets/images/add4.png":["assets/images/add4.png"],"assets/images/ai.png":["assets/images/ai.png"],"assets/images/background.png":["assets/images/background.png"],"assets/images/call.png":["assets/images/call.png"],"assets/images/contact_icon.png":["assets/images/contact_icon.png"],"assets/images/database.png":["assets/images/database.png"],"assets/images/desktop.png":["assets/images/desktop.png"],"assets/images/domain.png":["assets/images/domain.png"],"assets/images/download.png":["assets/images/download.png"],"assets/images/email.png":["assets/images/email.png"],"assets/images/hand.png":["assets/images/hand.png"],"assets/images/intelligent.png":["assets/images/intelligent.png"],"assets/images/java.svg":["assets/images/java.svg"],"assets/images/laptop.png":["assets/images/laptop.png"],"assets/images/machine.png":["assets/images/machine.png"],"assets/images/mail.png":["assets/images/mail.png"],"assets/images/messanger.png":["assets/images/messanger.png"],"assets/images/password.png":["assets/images/password.png"],"assets/images/people.png":["assets/images/people.png"],"assets/images/portfolio_pic.jpeg":["assets/images/portfolio_pic.jpeg"],"assets/images/pri_sign.png":["assets/images/pri_sign.png"],"assets/images/register.png":["assets/images/register.png"],"assets/images/signin.png":["assets/images/signin.png"],"assets/images/signout.png":["assets/images/signout.png"],"assets/images/user.png":["assets/images/user.png"],"packages/cupertino_icons/assets/CupertinoIcons.ttf":["packages/cupertino_icons/assets/CupertinoIcons.ttf"],"packages/font_awesome_flutter/lib/fonts/fa-brands-400.ttf":["packages/font_awesome_flutter/lib/fonts/fa-brands-400.ttf"],"packages/font_awesome_flutter/lib/fonts/fa-regular-400.ttf":["packages/font_awesome_flutter/lib/fonts/fa-regular-400.ttf"],"packages/font_awesome_flutter/lib/fonts/fa-solid-900.ttf":["packages/font_awesome_flutter/lib/fonts/fa-solid-900.ttf"]}